sapero_math/__init__.py
sapero_math/chebyshev.py
sapero_math/lcm.py
sapero_math/primegen.py
sapero_math-0.1.0.dist-info/LICENSE
sapero_math-0.1.0.dist-info/METADATA
sapero_math-0.1.0.dist-info/WHEEL
sapero_math-0.1.0.dist-info/top_level.txt
sapero_math-0.1.0.dist-info/RECORD
