Metadata-Version: 2.1
Name: sapero-math
Version: 0.1.0
Summary: Just a package for some math functions i needed on PyPI for easier access
Home-page: https://github.com/saperoi/sapero_math-py
Author: Saperoi
Author-email: uesugi.sapero@gmail.com
License: UNKNOWN
Project-URL: Bug Tracker, https://github.com/saperoi/sapero_math-py/issues
Platform: UNKNOWN
Classifier: Programming Language :: Python :: 3
Classifier: Operating System :: OS Independent
Classifier: License :: OSI Approved :: GNU General Public License v3 (GPLv3)
Requires-Python: >=3.6
License-File: LICENSE
